{
  "provider": "Stats Perform",
  "sport": "Futsal",
  "file": "sp-futsal.json",
  "openapi": {
    "title": "SDAPI - Futsal",
    "version": "v1",
    "description": "",
    "base_url": "https://api.performfeeds.com/futsaldata",
    "endpoint_count": 7,
    "endpoints": [
      {
        "method": "GET",
        "path": "/tournamentcalendar/{outletAuthKey}",
        "summary": "",
        "operationId": "getTournamentCalendars",
        "tags": [
          "OT2 - Tournament Calendars"
        ],
        "parameters": [
          {
            "name": "stages",
            "in": "query",
            "required": false,
            "description": "Include stages information"
          },
          {
            "name": "comp",
            "in": "query",
            "required": false,
            "description": "Competition"
          },
          {
            "name": "ctst",
            "in": "query",
            "required": false,
            "description": "Contestant"
          },
          {
            "name": "stg",
            "in": "query",
            "required": false,
            "description": "Stage"
          },
          {
            "name": "outletAuthKey",
            "in": "path",
            "required": true,
            "description": "Outlet auth key"
          },
          {
            "name": "_fmt",
            "in": "query",
            "required": true,
            "description": "Format"
          },
          {
            "name": "_rt",
            "in": "query",
            "required": true,
            "description": "Mode"
          },
          {
            "name": "_clbk",
            "in": "query",
            "required": false,
            "description": "JSONP callback function"
          }
        ]
      },
      {
        "method": "GET",
        "path": "/tournamentcalendar/{outletAuthKey}/authorized",
        "summary": "",
        "operationId": "getAuthorizedTournamentCalendars",
        "tags": [
          "OT2 - Tournament Calendars"
        ],
        "parameters": [
          {
            "name": "stages",
            "in": "query",
            "required": false,
            "description": "Include stages information"
          },
          {
            "name": "comp",
            "in": "query",
            "required": false,
            "description": "Competition"
          },
          {
            "name": "ctst",
            "in": "query",
            "required": false,
            "description": "Contestant"
          },
          {
            "name": "outletAuthKey",
            "in": "path",
            "required": true,
            "description": "Outlet auth key"
          },
          {
            "name": "_fmt",
            "in": "query",
            "required": true,
            "description": "Format"
          },
          {
            "name": "_rt",
            "in": "query",
            "required": true,
            "description": "Mode"
          },
          {
            "name": "_clbk",
            "in": "query",
            "required": false,
            "description": "JSONP callback function"
          }
        ]
      },
      {
        "method": "GET",
        "path": "/tournamentcalendar/{outletAuthKey}/active",
        "summary": "",
        "operationId": "getActiveTournamentCalendars",
        "tags": [
          "OT2 - Tournament Calendars"
        ],
        "parameters": [
          {
            "name": "stages",
            "in": "query",
            "required": false,
            "description": "Include stages information"
          },
          {
            "name": "comp",
            "in": "query",
            "required": false,
            "description": "Competition"
          },
          {
            "name": "ctst",
            "in": "query",
            "required": false,
            "description": "Contestant"
          },
          {
            "name": "outletAuthKey",
            "in": "path",
            "required": true,
            "description": "Outlet auth key"
          },
          {
            "name": "_fmt",
            "in": "query",
            "required": true,
            "description": "Format"
          },
          {
            "name": "_rt",
            "in": "query",
            "required": true,
            "description": "Mode"
          },
          {
            "name": "_clbk",
            "in": "query",
            "required": false,
            "description": "JSONP callback function"
          }
        ]
      },
      {
        "method": "GET",
        "path": "/tournamentcalendar/{outletAuthKey}/active/authorized",
        "summary": "",
        "operationId": "getActiveAuthorizedTournamentCalendars",
        "tags": [
          "OT2 - Tournament Calendars"
        ],
        "parameters": [
          {
            "name": "stages",
            "in": "query",
            "required": false,
            "description": "Include stages information"
          },
          {
            "name": "comp",
            "in": "query",
            "required": false,
            "description": "Competition"
          },
          {
            "name": "ctst",
            "in": "query",
            "required": false,
            "description": "Contestant"
          },
          {
            "name": "outletAuthKey",
            "in": "path",
            "required": true,
            "description": "Outlet auth key"
          },
          {
            "name": "_fmt",
            "in": "query",
            "required": true,
            "description": "Format"
          },
          {
            "name": "_rt",
            "in": "query",
            "required": true,
            "description": "Mode"
          },
          {
            "name": "_clbk",
            "in": "query",
            "required": false,
            "description": "JSONP callback function"
          }
        ]
      },
      {
        "method": "GET",
        "path": "/standings/{outletAuthKey}",
        "summary": "",
        "operationId": "getTeamStandingsByParams",
        "tags": [
          "TM2 - Team Standings"
        ],
        "parameters": [
          {
            "name": "outletAuthKey",
            "in": "path",
            "required": true,
            "description": "Outlet auth key"
          },
          {
            "name": "tmcl",
            "in": "query",
            "required": true,
            "description": "Tournament calendar"
          },
          {
            "name": "_fmt",
            "in": "query",
            "required": true,
            "description": "Format"
          },
          {
            "name": "_rt",
            "in": "query",
            "required": true,
            "description": "Mode"
          },
          {
            "name": "_clbk",
            "in": "query",
            "required": false,
            "description": "JSONP callback function"
          }
        ]
      },
      {
        "method": "GET",
        "path": "/match/{outletAuthKey}",
        "summary": "",
        "operationId": "getMatchByParams",
        "tags": [
          "MA1 - Match"
        ],
        "parameters": [
          {
            "name": "outletAuthKey",
            "in": "path",
            "required": true,
            "description": "Outlet auth key"
          },
          {
            "name": "tmcl",
            "in": "query",
            "required": false,
            "description": "Tournament calendar"
          },
          {
            "name": "comp",
            "in": "query",
            "required": false,
            "description": "Competition"
          },
          {
            "name": "_pgSz",
            "in": "query",
            "required": false,
            "description": "Page size"
          },
          {
            "name": "_pgNm",
            "in": "query",
            "required": false,
            "description": "Page number"
          },
          {
            "name": "stg",
            "in": "query",
            "required": false,
            "description": "Stage"
          },
          {
            "name": "mt.mDt",
            "in": "query",
            "required": false,
            "description": "Match date range. Format: '[YYYY-MM-DDThh:mm:ssZ TO YYYY-MM-DDThh:mm:ssZ]' including brackets"
          },
          {
            "name": "live",
            "in": "query",
            "required": false,
            "description": "Live"
          },
          {
            "name": "status",
            "in": "query",
            "required": false,
            "description": "Match status"
          },
          {
            "name": "_fmt",
            "in": "query",
            "required": true,
            "description": "Format"
          },
          {
            "name": "_rt",
            "in": "query",
            "required": true,
            "description": "Mode"
          },
          {
            "name": "_clbk",
            "in": "query",
            "required": false,
            "description": "JSONP callback function"
          }
        ]
      },
      {
        "method": "GET",
        "path": "/match/{outletAuthKey}/{matchUuid}",
        "summary": "",
        "operationId": "getMatch",
        "tags": [
          "MA1 - Match"
        ],
        "parameters": [
          {
            "name": "outletAuthKey",
            "in": "path",
            "required": true,
            "description": "Outlet auth key"
          },
          {
            "name": "matchUuid",
            "in": "path",
            "required": true,
            "description": "Fixture/match uuid"
          },
          {
            "name": "live",
            "in": "query",
            "required": false,
            "description": "Live"
          },
          {
            "name": "_fmt",
            "in": "query",
            "required": true,
            "description": "Format"
          },
          {
            "name": "_rt",
            "in": "query",
            "required": true,
            "description": "Mode"
          },
          {
            "name": "_clbk",
            "in": "query",
            "required": false,
            "description": "JSONP callback function"
          }
        ]
      }
    ],
    "tags": [
      {
        "name": "MA1 - Match",
        "description": ""
      },
      {
        "name": "OT2 - Tournament Calendars",
        "description": ""
      },
      {
        "name": "TM2 - Team Standings",
        "description": ""
      }
    ]
  },
  "sdapi_pages": [
    {
      "title": "Sports Data Futsal API- Match feed (MA1)",
      "url": "https://documentation.statsperform.com/docs/rh/sdapi/Topics/futsal/opta-sdapi-futsal-api-match.htm",
      "sport": "futsal",
      "feed_codes": [
        "MA1"
      ],
      "headings": [
        "Sports Data Futsal API- Match feed (MA1)",
        "Overview",
        "Required Compliance:",
        "How Often Should I Poll The Feed?",
        "Match (MA1) Guide",
        "Query Parameters And Example Request Parameters",
        "Sample Calls",
        "Feed Output"
      ],
      "tables": [
        [
          [
            "Updated",
            "Polling frequency"
          ],
          [
            "On any update on a match time, date, teams, competition, round, or season",
            "\u2022 For fixtures: once per 24 hours \u2022 For a live match or match series: once every 30 seconds"
          ]
        ],
        [
          [
            "Usage",
            "Feed"
          ],
          [
            "GET detailed information for a specific fixture",
            "/futsaldata/match/{outletAuthKey}/{fixtureUuid}? {queryParameters}"
          ],
          [
            "GET detailed information for a list of matches for the specified competition or tournament calendar, according to the sp",
            "/futsaldata/match/{outletAuthKey}?{queryParameters}"
          ]
        ],
        [
          [
            "Query parameter",
            "Value and description"
          ],
          [
            "fixture/match UUID",
            "Get detailed information about one fixture by passing the fixture/match UUID as a path parameter (the asset/resource) in"
          ],
          [
            "comp",
            "Get information about matches only for a specific competition . Pass the competition UUID to the comp parameter. GET htt"
          ],
          [
            "tmcl",
            "Get information about matches only for the specified tournament calendar . Pass the tournament calendar UUID to the tmcl"
          ],
          [
            "live",
            "Get the score and match result for fixtures. Note: This information is returned in the liveData element when the call co"
          ],
          [
            "_pgNm + _pgSz",
            "Get data only in the specified page size and/or page number . All results are returned in pages and these parameters hel"
          ]
        ],
        [
          [
            "Nesting",
            "matches"
          ],
          [
            "Description",
            "Optional. Root element of the fields related to matches (XML only) Note: Not present in JSON feed response, where the ro"
          ],
          [
            ""
          ],
          [
            "Attribute (XML only)",
            "xmlns:futsaldata"
          ],
          [
            "Description",
            "Required . Schema reference (XML only)"
          ],
          [
            "Values",
            "http://www.performgroup.com/schema/futsaldata"
          ]
        ],
        [
          [
            "Nesting",
            "matches/match or: match"
          ],
          [
            "Description",
            "Required. Root element of the fields related to a match"
          ],
          [
            ""
          ],
          [
            "Attribute (XML only)",
            "xmlns:futsaldata"
          ],
          [
            "Description",
            "Required. Schema reference (XML only)"
          ],
          [
            "Values",
            "http://www.performgroup.com/schema/futsaldata"
          ]
        ]
      ]
    },
    {
      "title": "Sports Data Futsal API- Team Standings feed (TM2)",
      "url": "https://documentation.statsperform.com/docs/rh/sdapi/Topics/futsal/opta-sdapi-futsal-api-team-standings.htm",
      "sport": "futsal",
      "feed_codes": [
        "TM2"
      ],
      "headings": [
        "Sports Data Futsal API- Team Standings feed (TM2)",
        "Overview",
        "Required Compliance:",
        "How Often Should I Poll The Feed?",
        "Team Standings (OT2) Guide",
        "Query Parameters And Example Request Parameters",
        "Sample Calls",
        "Feed Output"
      ],
      "tables": [
        [
          [
            "Updated",
            "Polling frequency"
          ],
          [
            "On any update to a tournament calendar (season), competition, match status/result",
            "No more frequently than one URL poll every 30 seconds"
          ]
        ],
        [
          [
            "Usage",
            "Feed"
          ],
          [
            "GET team standings data according to specified parameter values",
            "/futsaldata/standings/{outletAuthKey}?{queryParameters}"
          ]
        ],
        [
          [
            "Query parameter",
            "Value and description"
          ],
          [
            "tmcl",
            "Get information about matches only for the specified tournament calendar . Pass the tournament calendar UUID to the tmcl"
          ]
        ],
        [
          [
            "Nesting",
            "teamStandings"
          ],
          [
            "Description",
            "Required/Optional . Root element of the fields related to the team standings information (XML only) Note: A named teamSt"
          ],
          [
            ""
          ],
          [
            "Attribute",
            "lastUpdated"
          ],
          [
            "Description",
            "Required . The UTC date and time (timestamp) of when the Standings feed information/record was last updated"
          ],
          [
            "Values",
            "Date/Time - in the format: YYYY-MM-DDThh:mm:ssZ"
          ],
          [
            ""
          ],
          [
            "Only present in XML (not JSON)"
          ]
        ],
        [
          [
            "Nesting",
            "teamStandings/sport"
          ],
          [
            "Description",
            "Required . Root element of the fields related to the sport. Value (XML only): String giving the sport name"
          ],
          [
            ""
          ],
          [
            "Attribute",
            "id"
          ],
          [
            "Description",
            "Required . Unique ID (UUID) of the sport"
          ],
          [
            "Values",
            "String ( Alphanumeric - UUID )"
          ],
          [
            ""
          ],
          [
            "Attribute",
            "name (JSON only)"
          ]
        ]
      ]
    },
    {
      "title": "Sports DataFutsal API Index and User Guide",
      "url": "https://documentation.statsperform.com/docs/rh/sdapi/Topics/futsal/index.htm",
      "sport": "futsal",
      "feed_codes": [],
      "headings": [
        "Sports DataFutsal API Index and User Guide",
        "Required Compliance:",
        "Futsal API - Overview",
        "Futsal API - Available Feeds"
      ],
      "tables": [
        [
          [
            "Element",
            "Definition"
          ],
          [
            "{protocol}",
            "https is the default request type"
          ],
          [
            "{requestDomain}",
            "Request domain to access the Sports Data API. For most clients, this is the default: api.performfeeds.com Use the defaul"
          ],
          [
            "{feedResource}",
            "Resource of the Sports Data API. In this case, the Futsal API: futsaldata"
          ],
          [
            "{feedName}",
            "Feed name of the resource, in the case of the Futsal API. For example: standings"
          ],
          [
            "{outletAuthKey}",
            "Outlet Authentication Key . A unique 26-character alphanumeric UUID which is unique to each outlet. Any requests made wi"
          ],
          [
            "{queryParameters}",
            "Query parameters . There are required and optional parameters. Optional parameters can help you to search the feed and c"
          ]
        ],
        [
          [
            "Feed",
            "Endpoint",
            "Reference"
          ],
          [
            "Tournament Calendars (OT2) Tournament Calendars (OT2) Provides basic information about the tournament calendars - the in",
            "/futsaldata/tournamentcalendar/ {outletAuthKey}",
            "User Guide"
          ],
          [
            "Match (MA1) Match (MA1) Provides a detailed fixture list with match details such as date, kick-off time, contestants, co",
            "/futsaldata/match/{outletAuthKey}",
            "User Guide"
          ],
          [
            "Team Standings (TM2) Team Standings (TM2) Provides data to create a league table - position, points, matches won/lost/dr",
            "/futsaldata/standings/{outletAuthKey}",
            "User Guide"
          ]
        ]
      ]
    },
    {
      "title": "Sports Data Futsal API- Tournament Calendars feed (OT2)",
      "url": "https://documentation.statsperform.com/docs/rh/sdapi/Topics/futsal/opta-sdapi-futsal-api-tournament-calendars.htm",
      "sport": "futsal",
      "feed_codes": [
        "OT2"
      ],
      "headings": [
        "Sports Data Futsal API- Tournament Calendars feed (OT2)",
        "Overview",
        "Required Compliance:",
        "How Often Should I Poll The Feed?",
        "Tournament Calendars (OT2) Guide",
        "Query Parameters And Example Request Parameters",
        "Endpoints",
        "Sample Calls",
        "Feed Output"
      ],
      "tables": [
        [
          [
            "Updated",
            "Polling frequency"
          ],
          [
            "On any update on seasons, teams, rounds",
            "Once every 24 hours"
          ]
        ],
        [
          [
            "Usage",
            "Feed"
          ],
          [
            "GET a list of Tournament Calendars according to the specified mandatory (and optional) parameter values",
            "/futsaldata/tournamentcalendar/{outletAuthKey}"
          ],
          [
            "GET a list of authorized Tournament Calendars and according to the specified mandatory (and optional) parameter values",
            "/futsaldata/tournamentcalendar/{outletAuthKey}/ authorized?{queryParameters}"
          ],
          [
            "GET a list of authorized and active Tournament Calendars and according to the specified mandatory (and optional) paramet",
            "/futsaldata/tournamentcalendar/{outletAuthKey}/ active?{queryParameters}"
          ]
        ],
        [
          [
            "Query parameter",
            "Value and description"
          ],
          [
            "comp",
            "Get tournament calendar information only for the specified competition . Pass the competition UUID to the comp parameter"
          ],
          [
            "ctst",
            "Get tournament calendar information only for the specified contestant (the opposition in a fixture, such as a sports tea"
          ],
          [
            "stages",
            "Get or exclude the following stages , series , and standings information of a tournament calendar: All stages including "
          ]
        ],
        [
          [
            "GET the active (usually the current/most recent) tournament calendars only.",
            "/futsaldata/tournamentcalendar/{outletAuthKey}/ active"
          ],
          [
            "GET authorized tournament calendars only (those you have access to view).",
            "/futsaldata/tournamentcalendar/{outletAuthKey}/ authorized"
          ]
        ],
        [
          [
            "Endpoint + Query parameter",
            "Value and description"
          ],
          [
            "/active + comp",
            "Get the active (usually the current/most recent) tournament calendars only for the specified competition UUID . GET http"
          ],
          [
            "/active + ctst",
            "Get the active (usually the current/most recent) tournament calendars only for the specified contestant UUID . GET https"
          ],
          [
            "/authorized + comp",
            "Get the authorized tournament calendars only for the specified competition UUID . Pass the competition UUID to the comp "
          ],
          [
            "/authorized + ctst",
            "Get Tournament Calendar information for the specified contestant only (the opposition in a fixture, such as a sports tea"
          ],
          [
            "/authorized + ctst + comp",
            "Get Tournament Calendar information for the specified contestant only (the opposition in a fixture, such as a sports tea"
          ]
        ]
      ]
    }
  ]
}